{
  "id": "tooling-status-parser",
  "title": "Tooling: status parser with tests",
  "skill_ids": [
    "cpp.tooling.debugging_method",
    "cpp.tooling.unit_testing",
    "cpp.tooling.regression_testing",
    "cpp.tooling.warnings",
    "cpp.tooling.sanitizers",
    "cpp.tooling.cmake"
  ],
  "difficulty": "intermediate",
  "estimated_minutes": 35,
  "editable_files": ["status_parser.hpp"],
  "build_command": "cmake -S exercises/tooling-status-parser -B exercises/tooling-status-parser/work/build -DCPPFAN_IMPL_DIR=$PWD/exercises/tooling-status-parser/work -DCPPFAN_ENABLE_SANITIZERS=ON -DCMAKE_BUILD_TYPE=Debug && cmake --build exercises/tooling-status-parser/work/build",
  "test_command": "ctest --test-dir exercises/tooling-status-parser/work/build --output-on-failure",
  "required_tests": [
    "test_parses_ok_status",
    "test_parses_error_status",
    "test_rejects_missing_message_boundary",
    "test_rejects_negative_code_adversarial",
    "test_regression_preserves_message_spaces"
  ],
  "hints": [
    "Parse the status word, numeric code, and the rest of the line as the message.",
    "Treat malformed input as {false, -1, \"malformed\"}; validate negative codes separately.",
    "Keep the message after the code intact except for one leading separator space."
  ],
  "project_lab": "debugging-toolchain-lab"
}
